LICENSE.txt
MANIFEST.in
README.rst
setup.py
pyspeakrec/__init__.py
pyspeakrec/audio_manip.py
pyspeakrec/enroll.py
pyspeakrec/test.py
pyspeakrec/train.py
pyspeakrec.egg-info/PKG-INFO
pyspeakrec.egg-info/SOURCES.txt
pyspeakrec.egg-info/dependency_links.txt
pyspeakrec.egg-info/not-zip-safe
pyspeakrec.egg-info/requires.txt
pyspeakrec.egg-info/top_level.txt