Metadata-Version: 1.1
Name: pyspeakrec
Version: 0.1.0
Summary: A Speaker Recognition tool in Python
Home-page: https://github.com/AKBoles/pyspeakrec
Author: Andrew Boles
Author-email: andrew.boles@my.utsa.edu
License: MIT
Keywords: speaker recognition,machine learning
Platform: UNKNOWN
Classifier: Development Status :: 3 - Alpha
Classifier: Programming Language :: Python :: 2.7
